audacitorch/__init__.py
audacitorch/core.py
audacitorch/utils.py
audacitorch-0.0.4.dist-info/LICENSE
audacitorch-0.0.4.dist-info/METADATA
audacitorch-0.0.4.dist-info/WHEEL
audacitorch-0.0.4.dist-info/top_level.txt
audacitorch-0.0.4.dist-info/RECORD
