Metadata-Version: 2.1
Name: audacitorch
Version: 0.0.4
Summary: UNKNOWN
Home-page: https://github.com/hugofloresgarcia/audacitorch
Author: Hugo Flores Garcia
Author-email: hf01049@georgiasouthern.edu
License: MIT
Platform: UNKNOWN
Classifier: License :: OSI Approved :: MIT License
License-File: LICENSE
Requires-Dist: torch (==1.9.0)
Requires-Dist: jsonschema
